[
    {
        "name": "ABC Traders",
        "product": "Rice"
    },
    {
        "name": "City Electronics",
        "product": "Mobile Chargers"
    },
    {
        "name": "Fresh Mart",
        "product": "Fruits"
    },
    {
        "name": "Star Textiles",
        "product": "Shirts"
    },
    {
        "name": "Sunrise Dairy",
        "product": "Milk"
    },
    {
        "name": "Metro Hardware",
        "product": "Tools"
    },
    {
        "name": "Green Garden",
        "product": "Plants"
    },
    {
        "name": "Quick Print ",
        "product": "Printing Services"
    }
]